LICENSE
MANIFEST.in
README.md
setup.cfg
setup.py
bmaquet_tap_zendesk.egg-info/PKG-INFO
bmaquet_tap_zendesk.egg-info/SOURCES.txt
bmaquet_tap_zendesk.egg-info/dependency_links.txt
bmaquet_tap_zendesk.egg-info/entry_points.txt
bmaquet_tap_zendesk.egg-info/requires.txt
bmaquet_tap_zendesk.egg-info/top_level.txt
tap_zendesk/__init__.py
tap_zendesk/discover.py
tap_zendesk/metrics.py
tap_zendesk/streams.py
tap_zendesk/sync.py
tap_zendesk/schemas/group_memberships.json
tap_zendesk/schemas/groups.json
tap_zendesk/schemas/macros.json
tap_zendesk/schemas/organizations.json
tap_zendesk/schemas/satisfaction_ratings.json
tap_zendesk/schemas/sla_policies.json
tap_zendesk/schemas/tags.json
tap_zendesk/schemas/ticket_audits.json
tap_zendesk/schemas/ticket_comments.json
tap_zendesk/schemas/ticket_fields.json
tap_zendesk/schemas/ticket_forms.json
tap_zendesk/schemas/ticket_metric_events.json
tap_zendesk/schemas/ticket_metrics.json
tap_zendesk/schemas/tickets.json
tap_zendesk/schemas/users.json
tap_zendesk/schemas/shared/attachments.json
tap_zendesk/schemas/shared/metadata.json
tap_zendesk/schemas/shared/via.json
test/test_all_streams.py
test/test_bookmarks.py
test/test_custom_fields_discover.py
test/test_minimal_selection.py