Metadata-Version: 2.1
Name: bmaquet-tap-zendesk
Version: 1.0.1
Summary: Singer.io tap for extracting data from the Zendesk API
Home-page: https://singer.io
Author: Stitch
License: UNKNOWN
Platform: UNKNOWN
Classifier: Programming Language :: Python :: 3 :: Only
Provides-Extra: dev
